arbitrage
