Metadata-Version: 1.1
Name: arbitrage
Version: 0.1.6
Summary: Get current coin (btc/eth/xrp) ticker from exchanges (bitflyer/btcbox/zaif/bitbank/quoinex)
Home-page: https://github.com/10mohi6/arbitrage-python
Author: 10mohi6
Author-email: 10.mohi.6.y@gmail.com
License: MIT
Keywords: arbitrage
Platform: UNKNOWN
Classifier: Development Status :: 4 - Beta
Classifier: Programming Language :: Python :: 3.6
Classifier: Intended Audience :: Financial and Insurance Industry
Classifier: Intended Audience :: Developers
Classifier: Intended Audience :: Information Technology
Classifier: Operating System :: OS Independent
Classifier: Topic :: Software Development :: Build Tools
Classifier: Topic :: Office/Business :: Financial :: Investment
Classifier: License :: OSI Approved :: MIT License
